odoo8_addon_mass_mailing_unique-8.0.1.0.0.99.dev12-py3.8-nspkg.pth
odoo_addons/mass_mailing_unique/README.rst
odoo_addons/mass_mailing_unique/__init__.py
odoo_addons/mass_mailing_unique/__openerp__.py
odoo_addons/mass_mailing_unique/hooks.py
odoo_addons/mass_mailing_unique/i18n/ca.po
odoo_addons/mass_mailing_unique/i18n/de.po
odoo_addons/mass_mailing_unique/i18n/es.po
odoo_addons/mass_mailing_unique/i18n/fi.po
odoo_addons/mass_mailing_unique/i18n/fr.po
odoo_addons/mass_mailing_unique/i18n/hr.po
odoo_addons/mass_mailing_unique/i18n/it.po
odoo_addons/mass_mailing_unique/i18n/mass_mailing_unique.pot
odoo_addons/mass_mailing_unique/i18n/sl.po
odoo_addons/mass_mailing_unique/images/error-duplicated-email.png
odoo_addons/mass_mailing_unique/images/error-duplicated-list.png
odoo_addons/mass_mailing_unique/models/__init__.py
odoo_addons/mass_mailing_unique/models/mass_mailing.py
odoo_addons/mass_mailing_unique/static/description/icon.png
odoo8_addon_mass_mailing_unique-8.0.1.0.0.99.dev12.dist-info/METADATA
odoo8_addon_mass_mailing_unique-8.0.1.0.0.99.dev12.dist-info/WHEEL
odoo8_addon_mass_mailing_unique-8.0.1.0.0.99.dev12.dist-info/namespace_packages.txt
odoo8_addon_mass_mailing_unique-8.0.1.0.0.99.dev12.dist-info/top_level.txt
odoo8_addon_mass_mailing_unique-8.0.1.0.0.99.dev12.dist-info/RECORD
